test_name/__init__.py
test_name/first.py
test_math_mukul-0.0.1.dist-info/METADATA
test_math_mukul-0.0.1.dist-info/WHEEL
test_math_mukul-0.0.1.dist-info/top_level.txt
test_math_mukul-0.0.1.dist-info/RECORD
